setup.py
distributions_arva/Binomialdistribution.py
distributions_arva/Gaussiandistribution.py
distributions_arva/Generaldistribution.py
distributions_arva/__init__.py
distributions_arva.egg-info/PKG-INFO
distributions_arva.egg-info/SOURCES.txt
distributions_arva.egg-info/dependency_links.txt
distributions_arva.egg-info/not-zip-safe
distributions_arva.egg-info/top_level.txt