Metadata-Version: 1.0
Name: distributions-arva
Version: 0.1
Summary: Gaussian and Binomial distributions
Home-page: UNKNOWN
Author: Aravindh Vangal
Author-email: aravindh1987@gmail.com
License: UNKNOWN
Platform: UNKNOWN
